[
    {
        "line": "Каховская",
        "stations": [
            {
                "lat": 55.655134,
                "lng": 37.648843,
                "name": "Каширская"
            },
            {
                "lat": 55.653663,
                "lng": 37.6208616,
                "name": "Варшавская"
            },
            {
                "lat": 55.6525055,
                "lng": 37.5969296,
                "name": "Каховская"
            }
        ]
    },
    {
        "line": "Арбатско-Покровская",
        "stations": [
            {
                "lat": 55.8084991,
                "lng": 37.79849280000001,
                "name": "Щёлковская"
            },
            {
                "lat": 55.794507,
                "lng": 37.799363,
                "name": "Первомайская"
            },
            {
                "lat": 55.787775,
                "lng": 37.78143499999999,
                "name": "Измайловская"
            },
            {
                "lat": 55.78845099999999,
                "lng": 37.749619,
                "name": "Партизанская"
            },
            {
                "lat": 55.78306,
                "lng": 37.719423,
                "name": "Семёновская"
            },
            {
                "lat": 55.782094,
                "lng": 37.705287,
                "name": "Электрозаводская"
            },
            {
                "lat": 55.7724663,
                "lng": 37.679113,
                "name": "Бауманская"
            },
            {
                "lat": 55.7585098,
                "lng": 37.6602746,
                "name": "Курская"
            },
            {
                "lat": 55.7564497,
                "lng": 37.6233539,
                "name": "Площадь Революции"
            },
            {
                "lat": 55.752161,
                "lng": 37.601518,
                "name": "Арбатская"
            },
            {
                "lat": 55.747933,
                "lng": 37.5836873,
                "name": "Смоленская"
            },
            {
                "lat": 55.7440118,
                "lng": 37.56733510000001,
                "name": "Киевская"
            },
            {
                "lat": 55.73588480000001,
                "lng": 37.5174924,
                "name": "Парк Победы"
            },
            {
                "lat": 55.72957599999999,
                "lng": 37.470717,
                "name": "Славянский бульвар"
            },
            {
                "lat": 55.7306809,
                "lng": 37.4452868,
                "name": "Кунцевская"
            },
            {
                "lat": 55.74061099999999,
                "lng": 37.416918,
                "name": "Молодёжная"
            },
            {
                "lat": 55.75683799999999,
                "lng": 37.408013,
                "name": "Крылатское"
            },
            {
                "lat": 55.803723,
                "lng": 37.403083,
                "name": "Строгино"
            },
            {
                "lat": 55.82547599999999,
                "lng": 37.38537,
                "name": "Мякинино"
            },
            {
                "lat": 55.83574900000001,
                "lng": 37.38199,
                "name": "Волоколамская"
            },
            {
                "lat": 55.846006,
                "lng": 37.361364,
                "name": "Митино"
            },
            {
                "lat": 55.85587599999999,
                "lng": 37.354181,
                "name": "Пятницкое шоссе"
            }
        ]
    },
    {
        "line": "Калужско-Рижская",
        "stations": [
            {
                "lat": 55.8875998,
                "lng": 37.6613918,
                "name": "Медведково"
            },
            {
                "lat": 55.8704204,
                "lng": 37.665132,
                "name": "Бабушкинская"
            },
            {
                "lat": 55.85560839999999,
                "lng": 37.6544465,
                "name": "Свиблово"
            },
            {
                "lat": 55.8459435,
                "lng": 37.6385031,
                "name": "Ботанический сад"
            },
            {
                "lat": 55.82106100000001,
                "lng": 37.641478,
                "name": "ВДНХ"
            },
            {
                "lat": 55.807779,
                "lng": 37.638693,
                "name": "Алексеевская"
            },
            {
                "lat": 55.792496,
                "lng": 37.636151,
                "name": "Рижская"
            },
            {
                "lat": 55.77970149999999,
                "lng": 37.6336099,
                "name": "Проспект Мира"
            },
            {
                "lat": 55.7723688,
                "lng": 37.6316918,
                "name": "Сухаревская"
            },
            {
                "lat": 55.76584,
                "lng": 37.636773,
                "name": "Тургеневская"
            },
            {
                "lat": 55.75393159999999,
                "lng": 37.6348886,
                "name": "Китай-город"
            },
            {
                "lat": 55.7407293,
                "lng": 37.62558540000001,
                "name": "Третьяковская"
            },
            {
                "lat": 55.7292498,
                "lng": 37.6113133,
                "name": "Октябрьская"
            },
            {
                "lat": 55.718815,
                "lng": 37.6081149,
                "name": "Шаболовская"
            },
            {
                "lat": 55.7117033,
                "lng": 37.5814546,
                "name": "Ленинский проспект"
            },
            {
                "lat": 55.687911,
                "lng": 37.573532,
                "name": "Академическая"
            },
            {
                "lat": 55.67798699999999,
                "lng": 37.562873,
                "name": "Профсоюзная"
            },
            {
                "lat": 55.670385,
                "lng": 37.554719,
                "name": "Новые Черёмушки"
            },
            {
                "lat": 55.65716699999999,
                "lng": 37.540428,
                "name": "Калужская"
            },
            {
                "lat": 55.64260299999999,
                "lng": 37.52644799999999,
                "name": "Беляево"
            },
            {
                "lat": 55.6346554,
                "lng": 37.51959009999999,
                "name": "Коньково"
            },
            {
                "lat": 55.6205011,
                "lng": 37.505881,
                "name": "Тёплый стан"
            },
            {
                "lat": 55.6061825,
                "lng": 37.5349539,
                "name": "Ясенево"
            },
            {
                "lat": 55.6019545,
                "lng": 37.5529046,
                "name": "Новоясеневская"
            }
        ]
    },
    {
        "line": "Кольцевая",
        "stations": [
            {
                "lat": 55.7351793,
                "lng": 37.5931278,
                "name": "Парк культуры"
            },
            {
                "lat": 55.7292498,
                "lng": 37.6113133,
                "name": "Октябрьская"
            },
            {
                "lat": 55.72898,
                "lng": 37.622529,
                "name": "Добрынинская"
            },
            {
                "lat": 55.731266,
                "lng": 37.636263,
                "name": "Павелецкая"
            },
            {
                "lat": 55.74245070000001,
                "lng": 37.6533745,
                "name": "Таганская"
            },
            {
                "lat": 55.7585098,
                "lng": 37.6602746,
                "name": "Курская"
            },
            {
                "lat": 55.7764063,
                "lng": 37.6561361,
                "name": "Комсомольская"
            },
            {
                "lat": 55.77970149999999,
                "lng": 37.6336099,
                "name": "Проспект Мира"
            },
            {
                "lat": 55.7796266,
                "lng": 37.6014405,
                "name": "Новослободская"
            },
            {
                "lat": 55.7771985,
                "lng": 37.5817828,
                "name": "Белорусская"
            },
            {
                "lat": 55.76024659999999,
                "lng": 37.5771211,
                "name": "Краснопресненская"
            },
            {
                "lat": 55.7440118,
                "lng": 37.56733510000001,
                "name": "Киевская"
            }
        ]
    },
    {
        "line": "Люблинско-Дмитровская",
        "stations": [
            {
                "lat": 55.79354319999999,
                "lng": 37.6168464,
                "name": "Марьина роща"
            },
            {
                "lat": 55.7817338,
                "lng": 37.614065,
                "name": "Достоевская"
            },
            {
                "lat": 55.767798,
                "lng": 37.621908,
                "name": "Трубная"
            },
            {
                "lat": 55.765802,
                "lng": 37.639251,
                "name": "Сретенский бульвар"
            },
            {
                "lat": 55.7560807,
                "lng": 37.6593866,
                "name": "Чкаловская"
            },
            {
                "lat": 55.7468006,
                "lng": 37.6795593,
                "name": "Римская"
            },
            {
                "lat": 55.73227499999999,
                "lng": 37.665521,
                "name": "Крестьянская застава"
            },
            {
                "lat": 55.717828,
                "lng": 37.676631,
                "name": "Дубровка"
            },
            {
                "lat": 55.706289,
                "lng": 37.685595,
                "name": "Кожуховская"
            },
            {
                "lat": 55.693163,
                "lng": 37.726901,
                "name": "Печатники"
            },
            {
                "lat": 55.690904,
                "lng": 37.75332,
                "name": "Волжская"
            },
            {
                "lat": 55.67568,
                "lng": 37.761759,
                "name": "Люблино"
            },
            {
                "lat": 55.6590248,
                "lng": 37.7497575,
                "name": "Братиславская"
            },
            {
                "lat": 55.650167,
                "lng": 37.743734,
                "name": "Марьино"
            },
            {
                "lat": 55.63346199999999,
                "lng": 37.744072,
                "name": "Борисово"
            },
            {
                "lat": 55.6202081,
                "lng": 37.7432181,
                "name": "Шипиловская"
            },
            {
                "lat": 55.61203099999999,
                "lng": 37.744946,
                "name": "Зябликово"
            }
        ]
    },
    {
        "line": "Таганско-Краснопресненская",
        "stations": [
            {
                "lat": 55.86073099999999,
                "lng": 37.43646,
                "name": "Планерная"
            },
            {
                "lat": 55.850657,
                "lng": 37.43984,
                "name": "Сходненская"
            },
            {
                "lat": 55.8267074,
                "lng": 37.4375261,
                "name": "Тушинская"
            },
            {
                "lat": 55.81747799999999,
                "lng": 37.436128,
                "name": "Спартак"
            },
            {
                "lat": 55.8076908,
                "lng": 37.4655764,
                "name": "Щукинская"
            },
            {
                "lat": 55.79352,
                "lng": 37.493538,
                "name": "Октябрьское поле"
            },
            {
                "lat": 55.777524,
                "lng": 37.519501,
                "name": "Полежаевская"
            },
            {
                "lat": 55.773661,
                "lng": 37.546758,
                "name": "Беговая"
            },
            {
                "lat": 55.764703,
                "lng": 37.561451,
                "name": "Улица 1905 года"
            },
            {
                "lat": 55.760782,
                "lng": 37.581284,
                "name": "Баррикадная"
            },
            {
                "lat": 55.76495500000001,
                "lng": 37.605906,
                "name": "Пушкинская"
            },
            {
                "lat": 55.761548,
                "lng": 37.624413,
                "name": "Кузнецкий мост"
            },
            {
                "lat": 55.75393159999999,
                "lng": 37.6348886,
                "name": "Китай-город"
            },
            {
                "lat": 55.74245070000001,
                "lng": 37.6533745,
                "name": "Таганская"
            },
            {
                "lat": 55.731711,
                "lng": 37.666369,
                "name": "Пролетарская"
            },
            {
                "lat": 55.72499999999999,
                "lng": 37.68693,
                "name": "Волгоградский проспект"
            },
            {
                "lat": 55.708956,
                "lng": 37.731283,
                "name": "Текстильщики"
            },
            {
                "lat": 55.7054024,
                "lng": 37.7656694,
                "name": "Кузьминки"
            },
            {
                "lat": 55.716922,
                "lng": 37.79328,
                "name": "Рязанский проспект"
            },
            {
                "lat": 55.71565,
                "lng": 37.817908,
                "name": "Выхино"
            },
            {
                "lat": 55.702222,
                "lng": 37.851881,
                "name": "Лермонтовский проспект"
            },
            {
                "lat": 55.6844693,
                "lng": 37.8552019,
                "name": "Жулебино"
            },
            {
                "lat": 55.6746193,
                "lng": 37.8575975,
                "name": "Котельники"
            }
        ]
    },
    {
        "line": "Московское центральное кольцо",
        "stations": [
            {
                "lat": 55.8460423,
                "lng": 37.58931949999999,
                "name": "Владыкино"
            },
            {
                "lat": 55.84893,
                "lng": 37.571279,
                "name": "Окружная"
            },
            {
                "lat": 55.867296,
                "lng": 37.5409348,
                "name": "Лихоборы"
            },
            {
                "lat": 55.839591,
                "lng": 37.520054,
                "name": "Коптево"
            },
            {
                "lat": 55.8258959,
                "lng": 37.496436,
                "name": "Балтийская"
            },
            {
                "lat": 55.81358909999999,
                "lng": 37.4869461,
                "name": "Стрешнево"
            },
            {
                "lat": 55.7990496,
                "lng": 37.4991066,
                "name": "Панфиловская"
            },
            {
                "lat": 55.777524,
                "lng": 37.519501,
                "name": "Зорге"
            },
            {
                "lat": 55.777364,
                "lng": 37.5071288,
                "name": "Хорошево"
            },
            {
                "lat": 55.757389,
                "lng": 37.525531,
                "name": "Шелепиха"
            },
            {
                "lat": 55.750015,
                "lng": 37.542048,
                "name": "Деловой центр"
            },
            {
                "lat": 55.740005,
                "lng": 37.534377,
                "name": "Кутузовская"
            },
            {
                "lat": 55.7209251,
                "lng": 37.5599288,
                "name": "Лужники"
            },
            {
                "lat": 55.7117033,
                "lng": 37.5814546,
                "name": "Площадь Гагарина"
            },
            {
                "lat": 55.689854,
                "lng": 37.605777,
                "name": "Крымская"
            },
            {
                "lat": 55.6902947,
                "lng": 37.619574,
                "name": "Верхние котлы"
            },
            {
                "lat": 55.704407,
                "lng": 37.623024,
                "name": "ЗИЛ"
            },
            {
                "lat": 55.7086,
                "lng": 37.6573453,
                "name": "Автозаводская"
            },
            {
                "lat": 55.717828,
                "lng": 37.676631,
                "name": "Дубровка"
            },
            {
                "lat": 55.7182971,
                "lng": 37.697751,
                "name": "Угрешская"
            },
            {
                "lat": 55.724146,
                "lng": 37.716998,
                "name": "Новохохловская"
            },
            {
                "lat": 55.732037,
                "lng": 37.728156,
                "name": "Нижегородская"
            },
            {
                "lat": 55.747112,
                "lng": 37.73783299999999,
                "name": "Андроновка"
            },
            {
                "lat": 55.758303,
                "lng": 37.751523,
                "name": "Шоссе энтузиастов"
            },
            {
                "lat": 55.771528,
                "lng": 37.745102,
                "name": "Соколиная гора"
            },
            {
                "lat": 55.787775,
                "lng": 37.78143499999999,
                "name": "Измайлово"
            },
            {
                "lat": 55.803681,
                "lng": 37.74117529999999,
                "name": "Локомотив"
            },
            {
                "lat": 55.8154055,
                "lng": 37.7329261,
                "name": "Бульвар Рокоссовского"
            },
            {
                "lat": 55.8293,
                "lng": 37.702428,
                "name": "Белокаменная"
            },
            {
                "lat": 55.839704,
                "lng": 37.666918,
                "name": "Ростокино"
            },
            {
                "lat": 55.8459435,
                "lng": 37.6385031,
                "name": "Ботанический сад"
            }
        ]
    },
    {
        "line": "Филёвская",
        "stations": [
            {
                "lat": 55.7306809,
                "lng": 37.4452868,
                "name": "Кунцевская"
            },
            {
                "lat": 55.7361492,
                "lng": 37.4676943,
                "name": "Пионерская"
            },
            {
                "lat": 55.73957000000001,
                "lng": 37.48330199999999,
                "name": "Филевский парк"
            },
            {
                "lat": 55.743792,
                "lng": 37.497743,
                "name": "Багратионовская"
            },
            {
                "lat": 55.746099,
                "lng": 37.514797,
                "name": "Фили"
            },
            {
                "lat": 55.740005,
                "lng": 37.534377,
                "name": "Кутузовская"
            },
            {
                "lat": 55.73887800000001,
                "lng": 37.5483398,
                "name": "Студенческая"
            },
            {
                "lat": 55.7440118,
                "lng": 37.56733510000001,
                "name": "Киевская"
            },
            {
                "lat": 55.747933,
                "lng": 37.5836873,
                "name": "Смоленская"
            },
            {
                "lat": 55.752161,
                "lng": 37.601518,
                "name": "Арбатская"
            },
            {
                "lat": 55.752289,
                "lng": 37.608663,
                "name": "Александровский сад"
            },
            {
                "lat": 55.750015,
                "lng": 37.542048,
                "name": "Выставочная"
            },
            {
                "lat": 55.74780999999999,
                "lng": 37.533181,
                "name": "Международная"
            }
        ]
    },
    {
        "line": "Калининско-Солнцевская",
        "stations": [
            {
                "lat": 55.745106,
                "lng": 37.86401499999999,
                "name": "Новокосино"
            },
            {
                "lat": 55.751699,
                "lng": 37.816642,
                "name": "Новогиреево"
            },
            {
                "lat": 55.75118999999999,
                "lng": 37.786649,
                "name": "Перово"
            },
            {
                "lat": 55.758303,
                "lng": 37.751523,
                "name": "Шоссе Энтузиастов"
            },
            {
                "lat": 55.751619,
                "lng": 37.717218,
                "name": "Авиамоторная"
            },
            {
                "lat": 55.747297,
                "lng": 37.6807531,
                "name": "Площадь Ильича"
            },
            {
                "lat": 55.74108889999999,
                "lng": 37.6566532,
                "name": "Марксистская"
            },
            {
                "lat": 55.7407293,
                "lng": 37.62558540000001,
                "name": "Третьяковская"
            },
            {
                "lat": 55.750015,
                "lng": 37.542048,
                "name": "Деловой центр"
            },
            {
                "lat": 55.73588480000001,
                "lng": 37.5174924,
                "name": "Парк победы"
            }
        ]
    },
    {
        "line": "Московский монорельс",
        "stations": [
            {
                "lat": 55.819012,
                "lng": 37.578891,
                "name": "Тимирязевская"
            },
            {
                "lat": 55.8217654,
                "lng": 37.5891812,
                "name": "Улица Милашенкова"
            },
            {
                "lat": 55.821818,
                "lng": 37.608926,
                "name": "Телецентр"
            },
            {
                "lat": 55.82106100000001,
                "lng": 37.641478,
                "name": "Улица Академика Королёва"
            },
            {
                "lat": 55.824049,
                "lng": 37.638473,
                "name": "Выставочный центр"
            },
            {
                "lat": 55.8292094,
                "lng": 37.644801,
                "name": "Улица Сергея Эйзенштейна"
            }
        ]
    },
    {
        "line": "Сокольническая",
        "stations": [
            {
                "lat": 55.8154055,
                "lng": 37.7329261,
                "name": "Бульвар Рокоссовского"
            },
            {
                "lat": 55.803943,
                "lng": 37.744764,
                "name": "Черкизовская"
            },
            {
                "lat": 55.7962395,
                "lng": 37.7154778,
                "name": "Преображенская площадь"
            },
            {
                "lat": 55.78925,
                "lng": 37.679683,
                "name": "Сокольники"
            },
            {
                "lat": 55.7799958,
                "lng": 37.6661449,
                "name": "Красносельская"
            },
            {
                "lat": 55.7764063,
                "lng": 37.6561361,
                "name": "Комсомольская"
            },
            {
                "lat": 55.76908,
                "lng": 37.649106,
                "name": "Красные ворота"
            },
            {
                "lat": 55.7649152,
                "lng": 37.6383605,
                "name": "Чистые пруды"
            },
            {
                "lat": 55.75966,
                "lng": 37.62658100000001,
                "name": "Лубянка"
            },
            {
                "lat": 55.75722349999999,
                "lng": 37.6150129,
                "name": "Охотный ряд"
            },
            {
                "lat": 55.7522265,
                "lng": 37.6103187,
                "name": "Библиотека имени Ленина"
            },
            {
                "lat": 55.745155,
                "lng": 37.603031,
                "name": "Кропоткинская"
            },
            {
                "lat": 55.7351793,
                "lng": 37.5931278,
                "name": "Парк культуры"
            },
            {
                "lat": 55.727474,
                "lng": 37.580683,
                "name": "Фрунзенская"
            },
            {
                "lat": 55.7224328,
                "lng": 37.5620735,
                "name": "Спортивная"
            },
            {
                "lat": 55.7115933,
                "lng": 37.561049,
                "name": "Воробьёвы горы"
            },
            {
                "lat": 55.6931907,
                "lng": 37.5345267,
                "name": "Университет"
            },
            {
                "lat": 55.676978,
                "lng": 37.50631,
                "name": "Проспект Вернадского"
            },
            {
                "lat": 55.66375000000001,
                "lng": 37.483152,
                "name": "Юго-Западная"
            },
            {
                "lat": 55.645646,
                "lng": 37.4729972,
                "name": "Тропарёво"
            },
            {
                "lat": 55.632969,
                "lng": 37.441696,
                "name": "Румянцево"
            },
            {
                "lat": 55.621907,
                "lng": 37.424165,
                "name": "Саларьево"
            }
        ]
    },
    {
        "line": "Бутовская",
        "stations": [
            {
                "lat": 55.60076100000001,
                "lng": 37.555577,
                "name": "Битцевский парк"
            },
            {
                "lat": 55.581433,
                "lng": 37.579106,
                "name": "Лесопарковая"
            },
            {
                "lat": 55.56934099999999,
                "lng": 37.576515,
                "name": "Улица Старокачаловская"
            },
            {
                "lat": 55.54814099999999,
                "lng": 37.55466,
                "name": "Улица Скобелевская"
            },
            {
                "lat": 55.54516899999999,
                "lng": 37.54229,
                "name": "Бульвар адмирала Ушакова"
            },
            {
                "lat": 55.542106,
                "lng": 37.531716,
                "name": "Улица Горчакова"
            },
            {
                "lat": 55.537949,
                "lng": 37.515382,
                "name": "Бунинская аллея"
            }
        ]
    },
    {
        "line": "Серпуховско-Тимирязевская",
        "stations": [
            {
                "lat": 55.897864,
                "lng": 37.587082,
                "name": "Алтуфьево"
            },
            {
                "lat": 55.8837138,
                "lng": 37.6047798,
                "name": "Бибирево"
            },
            {
                "lat": 55.863397,
                "lng": 37.604619,
                "name": "Отрадное"
            },
            {
                "lat": 55.8460423,
                "lng": 37.58931949999999,
                "name": "Владыкино"
            },
            {
                "lat": 55.83666100000001,
                "lng": 37.57535,
                "name": "Петровско-Разумовская"
            },
            {
                "lat": 55.819012,
                "lng": 37.578891,
                "name": "Тимирязевская"
            },
            {
                "lat": 55.8080834,
                "lng": 37.5813504,
                "name": "Дмитровская"
            },
            {
                "lat": 55.7942914,
                "lng": 37.5881988,
                "name": "Савёловская"
            },
            {
                "lat": 55.78174,
                "lng": 37.598943,
                "name": "Менделеевская"
            },
            {
                "lat": 55.771682,
                "lng": 37.620685,
                "name": "Цветной бульвар"
            },
            {
                "lat": 55.76593270000001,
                "lng": 37.6078576,
                "name": "Чеховская"
            },
            {
                "lat": 55.7503444,
                "lng": 37.6088658,
                "name": "Боровицкая"
            },
            {
                "lat": 55.73683,
                "lng": 37.6186425,
                "name": "Полянка"
            },
            {
                "lat": 55.72686599999999,
                "lng": 37.6257733,
                "name": "Серпуховская"
            },
            {
                "lat": 55.70867699999999,
                "lng": 37.622423,
                "name": "Тульская"
            },
            {
                "lat": 55.68300199999999,
                "lng": 37.621758,
                "name": "Нагатинская"
            },
            {
                "lat": 55.6728846,
                "lng": 37.610313,
                "name": "Нагорная"
            },
            {
                "lat": 55.662596,
                "lng": 37.605321,
                "name": "Нахимовский проспект"
            },
            {
                "lat": 55.651466,
                "lng": 37.5981134,
                "name": "Севастопольская"
            },
            {
                "lat": 55.64083300000001,
                "lng": 37.606228,
                "name": "Чертановская"
            },
            {
                "lat": 55.6234635,
                "lng": 37.6087977,
                "name": "Южная"
            },
            {
                "lat": 55.61232099999999,
                "lng": 37.604173,
                "name": "Пражская"
            },
            {
                "lat": 55.595155,
                "lng": 37.601373,
                "name": "Улица академика Янгеля"
            },
            {
                "lat": 55.583643,
                "lng": 37.596829,
                "name": "Аннино"
            },
            {
                "lat": 55.569497,
                "lng": 37.576439,
                "name": "Бульвар Дмитрия Донского"
            }
        ]
    },
    {
        "line": "Замоскворецкая",
        "stations": [
            {
                "lat": 55.632813,
                "lng": 37.766061,
                "name": "Алма-Атинская"
            },
            {
                "lat": 55.61386599999999,
                "lng": 37.744544,
                "name": "Красногвардейская"
            },
            {
                "lat": 55.61095299999999,
                "lng": 37.71909,
                "name": "Домодедовская"
            },
            {
                "lat": 55.613195,
                "lng": 37.694966,
                "name": "Орехово"
            },
            {
                "lat": 55.62145599999999,
                "lng": 37.669453,
                "name": "Царицыно"
            },
            {
                "lat": 55.63477020000001,
                "lng": 37.65705990000001,
                "name": "Кантемировская"
            },
            {
                "lat": 55.655134,
                "lng": 37.648843,
                "name": "Каширская"
            },
            {
                "lat": 55.6795093,
                "lng": 37.6633652,
                "name": "Коломенская"
            },
            {
                "lat": 55.693704,
                "lng": 37.664496,
                "name": "Технопарк"
            },
            {
                "lat": 55.7086,
                "lng": 37.6573453,
                "name": "Автозаводская"
            },
            {
                "lat": 55.731266,
                "lng": 37.636263,
                "name": "Павелецкая"
            },
            {
                "lat": 55.7424277,
                "lng": 37.6292832,
                "name": "Новокузнецкая"
            },
            {
                "lat": 55.7576,
                "lng": 37.618738,
                "name": "Театральная"
            },
            {
                "lat": 55.765362,
                "lng": 37.6049562,
                "name": "Тверская"
            },
            {
                "lat": 55.7703912,
                "lng": 37.5960546,
                "name": "Маяковская"
            },
            {
                "lat": 55.7771985,
                "lng": 37.5817828,
                "name": "Белорусская"
            },
            {
                "lat": 55.7891159,
                "lng": 37.5595953,
                "name": "Динамо"
            },
            {
                "lat": 55.800365,
                "lng": 37.532628,
                "name": "Аэропорт"
            },
            {
                "lat": 55.80478,
                "lng": 37.515548,
                "name": "Сокол"
            },
            {
                "lat": 55.819087,
                "lng": 37.497888,
                "name": "Войковская"
            },
            {
                "lat": 55.83993299999999,
                "lng": 37.486703,
                "name": "Водный стадион"
            },
            {
                "lat": 55.8551525,
                "lng": 37.4760633,
                "name": "Речной вокзал"
            }
        ]
    }
]